flosy/__init__.py
flosy-0.0.1.dist-info/LICENSE
flosy-0.0.1.dist-info/WHEEL
flosy-0.0.1.dist-info/METADATA
flosy-0.0.1.dist-info/RECORD
